tackle/__init__.py
tackle/db_models.py
tackle/flask_utils.py
tackle/manage_auth_tokens.py
tackle/manage_db.py
tackle/prometheus_utils.py
tackle/rest_api/__init__.py
tackle/rest_api/dashboard_wrapper.py
tackle/rest_api/health_wrapper.py
tackle/rest_api/wrapper_util.py
tackle/rest_api/flask_server/__init__.py
tackle/rest_api/flask_server/controllers/__init__.py
tackle/rest_api/flask_server/controllers/controller_util.py
tackle/rest_api/flask_server/controllers/dashboard_controller.py
tackle/rest_api/flask_server/controllers/health_controller.py
tackle/rest_api/flask_server/swagger/swagger.yaml
tackle/rest_api/flask_server/tests/__init__.py
tackle/rest_api/flask_server/tests/test_rest_dashboard.py
tackle/rest_api/flask_server/tests/test_rest_health_endpoint.py
tackle/tests/__init__.py
api_tackle-0.2.dist-info/LICENSE.txt
api_tackle-0.2.dist-info/METADATA
api_tackle-0.2.dist-info/WHEEL
api_tackle-0.2.dist-info/top_level.txt
api_tackle-0.2.dist-info/RECORD
