Metadata-Version: 2.1
Name: api-tackle
Version: 0.2
Summary: API Tackle - Simple Python REST API Framework
Home-page: https://github.com/praekelt/api-tackle
Author: bernardt@preakelt.com
Author-email: bernardt@preakelt.com
License: BSD 3-Clause License
Keywords: REST API framework
Platform: UNKNOWN
Classifier: Development Status :: 5 - Production/Stable
Classifier: Intended Audience :: Developers
Classifier: Topic :: Scientific/Engineering :: Artificial Intelligence
Classifier: License :: OSI Approved :: BSD License
Classifier: Programming Language :: Python :: 3
Requires-Dist: alembic (==1.4.2)
Requires-Dist: appdirs (==1.4.3)
Requires-Dist: attrs (==19.3.0)
Requires-Dist: certifi (==2020.4.5.1)
Requires-Dist: chardet (==3.0.4)
Requires-Dist: click (==7.1.2)
Requires-Dist: clickclick (==1.2.2)
Requires-Dist: connexion[swagger-ui] (==2.7.0)
Requires-Dist: flask-cors (==3.0.8)
Requires-Dist: flask-migrate (==2.5.3)
Requires-Dist: flask-script (==2.0.6)
Requires-Dist: flask-sqlalchemy (==2.4.1)
Requires-Dist: flask-testing (==0.8.0)
Requires-Dist: flask (==1.1.2)
Requires-Dist: gunicorn (==20.0.4)
Requires-Dist: idna (==2.9)
Requires-Dist: importlib-metadata (==1.6.0)
Requires-Dist: inflection (==0.4.0)
Requires-Dist: itsdangerous (==1.1.0)
Requires-Dist: jinja2 (==2.11.2)
Requires-Dist: jsonschema (==3.2.0)
Requires-Dist: mako (==1.1.2)
Requires-Dist: markupsafe (==1.1.1)
Requires-Dist: openapi-spec-validator (==0.2.8)
Requires-Dist: pip-tools (==5.1.0)
Requires-Dist: prometheus-client (==0.7.1)
Requires-Dist: psycopg2 (==2.8.5)
Requires-Dist: pyrsistent (==0.16.0)
Requires-Dist: python-dateutil (==2.8.1)
Requires-Dist: python-editor (==1.0.4)
Requires-Dist: pyyaml (==5.3.1)
Requires-Dist: requests (==2.23.0)
Requires-Dist: six (==1.14.0)
Requires-Dist: sqlalchemy (==1.3.16)
Requires-Dist: swagger-ui-bundle (==0.0.6)
Requires-Dist: urllib3 (==1.25.9)
Requires-Dist: werkzeug (==1.0.1)
Requires-Dist: wget (==3.2)
Requires-Dist: zipp (==3.1.0)
